pylash/__init__.py
pylash/core.py
pylash/display.py
pylash/events.py
pylash/geom.py
pylash/loaders.py
pylash/media.py
pylash/transitions.py
pylash/ui.py
pylash_engine-2.0.0a1.dist-info/LICENSE
pylash_engine-2.0.0a1.dist-info/METADATA
pylash_engine-2.0.0a1.dist-info/WHEEL
pylash_engine-2.0.0a1.dist-info/top_level.txt
pylash_engine-2.0.0a1.dist-info/RECORD
